interpreter/__init__.py
interpreter/__main__.py
interpreter/config.py
interpreter/log.py
interpreter/models.py
interpreter/ocr.py
interpreter/translate.py
interpreter/capture/__init__.py
interpreter/capture/convert.py
interpreter/capture/linux_wayland.py
interpreter/capture/linux_x11.py
interpreter/capture/macos.py
interpreter/capture/windows.py
interpreter/gpu/__init__.py
interpreter/gpu/linux.py
interpreter/gpu/macos.py
interpreter/gpu/windows.py
interpreter/gui/__init__.py
interpreter/gui/app.py
interpreter/gui/keyboard.py
interpreter/gui/main_window.py
interpreter/gui/ocr_config.py
interpreter/gui/workers.py
interpreter/overlay/__init__.py
interpreter/overlay/base.py
interpreter/overlay/linux.py
interpreter/overlay/macos.py
interpreter/overlay/windows.py
interpreter/permissions/__init__.py
interpreter/permissions/macos.py
interpreter/resources/icons/icon.icns
interpreter/resources/icons/icon.ico
interpreter/resources/icons/icon.png
interpreter_v2-2.17.2.dist-info/METADATA
interpreter_v2-2.17.2.dist-info/WHEEL
interpreter_v2-2.17.2.dist-info/entry_points.txt
interpreter_v2-2.17.2.dist-info/RECORD
