Metadata-Version: 2.4
Name: interpreter-v2
Version: 2.17.2
Summary: Offline screen translator for Japanese retro games
Author: qube
License-Expression: MIT
Keywords: games,japanese,ocr,retro,translation
Requires-Python: <3.13,>=3.11
Requires-Dist: ctranslate2
Requires-Dist: evdev-binary>=1.9.0; sys_platform == 'linux'
Requires-Dist: meikiocr
Requires-Dist: mss>=9.0.0
Requires-Dist: numpy
Requires-Dist: nvidia-cublas-cu12; sys_platform == 'win32' or sys_platform == 'linux'
Requires-Dist: nvidia-cudnn-cu12; sys_platform == 'win32' or sys_platform == 'linux'
Requires-Dist: onnxruntime
Requires-Dist: opencv-python
Requires-Dist: pillow>=10.0.0
Requires-Dist: pipewire-capture>=0.2.9; sys_platform == 'linux'
Requires-Dist: pygetwindow>=0.0.9; sys_platform == 'win32'
Requires-Dist: pynput>=1.7.0; sys_platform == 'darwin' or sys_platform == 'win32'
Requires-Dist: pyobjc-framework-cocoa>=12.1; sys_platform == 'darwin'
Requires-Dist: pyobjc-framework-quartz>=10.0; sys_platform == 'darwin'
Requires-Dist: pyside6>=6.6.0
Requires-Dist: python-xlib>=0.33; sys_platform == 'linux'
Requires-Dist: pyyaml>=6.0
Requires-Dist: requests
Requires-Dist: sentencepiece
Requires-Dist: structlog>=24.0.0
Requires-Dist: tqdm
Requires-Dist: windows-capture-interpreter>=1.5.1; sys_platform == 'win32'
